{"title":"C井定时器","uid":"5ff84a8c355f6485d89b09014ee560cf","slug":"C井定时器","date":"2021-10-21T03:24:21.000Z","updated":"2021-10-21T06:55:42.570Z","comments":true,"path":"api/articles/C井定时器.json","keywords":null,"cover":[],"content":"<h1 id=\"使用c-编写定时器程序\"><a href=\"#使用c-编写定时器程序\" class=\"headerlink\" title=\"使用c#编写定时器程序\"></a>使用c#编写定时器程序</h1><p>这是我第一个C#程序，是在B站跟着杜洋学习的，他的视频风格是比较愉快的，而且很生动仔细，一教一学的方式，感觉很好，希望我玩的开心！</p>\n<h1 id=\"创建工程\"><a href=\"#创建工程\" class=\"headerlink\" title=\"创建工程\"></a>创建工程</h1><img src=\"https://userblink.csdnimg.cn/20211021/qq_57475797/pic/8e33f5e4acb11e3e7439c22bcb7618a4-0.png?x-oss-process=image/watermark,image_bG9nby9jc2RuM3gucG5nP3gtb3NzLXByb2Nlc3M9aW1hZ2UvcmVzaXplLGhfMTY=,text_QHFxXzU3NDc1Nzk3,color_FFFFFF,size_17,shadow_100,t_100,g_se,order_0,align_2,interval_4\"  width=\"80%\" height=\"80%\" />\n\n<h1 id=\"为窗口添加窗体部件\"><a href=\"#为窗口添加窗体部件\" class=\"headerlink\" title=\"为窗口添加窗体部件\"></a>为窗口添加窗体部件</h1><img src=\"https://userblink.csdnimg.cn/20211021/qq_57475797/pic/d6d6e930b1c6b0948487ddd10ed748fe-0.png?x-oss-process=image/watermark,image_bG9nby9jc2RuM3gucG5nP3gtb3NzLXByb2Nlc3M9aW1hZ2UvcmVzaXplLGhfMTU=,text_QHFxXzU3NDc1Nzk3,color_FFFFFF,size_15,shadow_100,t_100,g_se,order_0,align_2,interval_4\" width=\"80%\" height=\"80%\" />\n\n<h1 id=\"为窗口内部添加逻辑\"><a href=\"#为窗口内部添加逻辑\" class=\"headerlink\" title=\"为窗口内部添加逻辑\"></a>为窗口内部添加逻辑</h1><img src=\"https://userblink.csdnimg.cn/20211021/qq_57475797/pic/db33497afe4816da5147d1e6e8d9aa37-0.png?x-oss-process=image/watermark,image_bG9nby9jc2RuM3gucG5nP3gtb3NzLXByb2Nlc3M9aW1hZ2UvcmVzaXplLGhfMTE=,text_QHFxXzU3NDc1Nzk3,color_FFFFFF,size_12,shadow_100,t_100,g_se,order_0,align_2,interval_4\" width=\"80%\" height=\"80%\" />\n\n<pre><code>using System;\nusing System.Collections.Generic;\nusing System.ComponentModel;\nusing System.Data;\nusing System.Drawing;\nusing System.Linq;\nusing System.Text;\nusing System.Threading.Tasks;\nusing System.Windows.Forms;\n\nnamespace WindowsFormsApp1\n&#123;\n    public partial class Form1 : Form\n    &#123;\n        int count;//当前时间\n        int time;//设置的定时间\n        public Form1()\n        &#123;\n            InitializeComponent();\n        &#125;\n\n        private void Form1_Load(object sender, EventArgs e)//在启动exe程序后，显示窗口之前，执行的语句\n        &#123;\n            int i;\n            for (i = 1; i &lt; 50; i++)\n            &#123;\n                comboBox1.Items.Add(i.ToString() + &quot; 秒&quot;);//为下拉输入的box添加选项\n            &#125;\n            \n            label3.Text = &quot;0秒&quot;;                         //为label（标签），添加文字\n\n\n        &#125;\n\n        private void Timer1_Tick(object sender, EventArgs e)//相当于单片机中的定时器中断函数，这里的是1000ms，即1s作为一个周期，1s运行一次该程序\n        &#123;\n            count++;                                            //每秒钟加一，相当于现在时间的秒数\n            label3.Text = (time -count).ToString() + &quot;秒&quot;;      //计算剩余秒数（时间），并且显示到标签\n            progressBar1.Value = count;                         //将时间数设为进度条的进度量，每秒发生一次改变，效果为进度条逐渐上升\n\n            if (count == time)\n            &#123;\n                timer1.Stop();\n                System.Media.SystemSounds.Asterisk.Play();\n                MessageBox.Show(&quot;时间到了！&quot;, &quot;提示&quot;);\n                //结束这一次的计时\n                //为下一次计时做准备\n                progressBar1.Value = 0;//初始化进度条最大容量\n                button1.Text = &quot;开始计时&quot;;//初始化按钮显示内容1\n                count = 0;\n                time = 0;\n            &#125;\n\n        &#125;\n\n        private void Button1_Click(object sender, EventArgs e)//单击按下按钮后，需要执行的程序\n        &#123;\n                if (button1.Text == &quot;开始计时&quot;)\n                &#123;\n                                \n                    time = Convert.ToInt16(comboBox1.Text.Substring(0, 2));//转化成10进制\n\n                    progressBar1.Maximum = time;//进度条开始的数值，即进度条最大数值\n\n                timer1.Start();//开始计时\n                    button1.Text = &quot;停止计时&quot;;\n                &#125;\n                else\n                &#123;\n\n                    button1.Text = &quot;开始计时&quot;;\n                    timer1.Stop();//停止计时\n\n                &#125;\n        &#125;\n\n        private void Label3_Click(object sender, EventArgs e)\n        &#123;\n\n        &#125;\n\n        private void ComboBox1_SelectedIndexChanged(object sender, EventArgs e)\n        &#123;\n\n        &#125;\n\n    &#125;\n&#125;\n</code></pre>\n<h1 id=\"生成exe文件\"><a href=\"#生成exe文件\" class=\"headerlink\" title=\"生成exe文件\"></a>生成exe文件</h1><img src=\"https://userblink.csdnimg.cn/20211021/qq_57475797/pic/cf807a7dbb4cbc810173b85ac5618ec1-0.png?x-oss-process=image/watermark,image_bG9nby9jc2RuM3gucG5nP3gtb3NzLXByb2Nlc3M9aW1hZ2UvcmVzaXplLGhfMTI=,text_QHFxXzU3NDc1Nzk3,color_FFFFFF,size_12,shadow_100,t_100,g_se,order_0,align_2,interval_4\" width=\"80%\" height=\"80%\" />","text":"使用c#编写定时器程序这是我第一个C#程序，是在B站跟着杜洋学习的，他的视频风格是比较愉快的，而且很生动仔细，一教一学的方式，感觉很好，希望我玩的开心！ 创建工程 为窗口添加窗体部件 为窗口内部添加逻辑 using System; using System.Collections...","link":"","photos":[],"count_time":{"symbolsCount":"2.7k","symbolsTime":"2 mins."},"categories":[{"name":"上位机","slug":"上位机","count":1,"path":"api/categories/上位机.json"}],"tags":[{"name":"c#","slug":"c","count":1,"path":"api/tags/c.json"}],"toc":"<ol class=\"toc\"><li class=\"toc-item toc-level-1\"><a class=\"toc-link\" href=\"#%E4%BD%BF%E7%94%A8c-%E7%BC%96%E5%86%99%E5%AE%9A%E6%97%B6%E5%99%A8%E7%A8%8B%E5%BA%8F\"><span class=\"toc-text\">使用c#编写定时器程序</span></a></li><li class=\"toc-item toc-level-1\"><a class=\"toc-link\" href=\"#%E5%88%9B%E5%BB%BA%E5%B7%A5%E7%A8%8B\"><span class=\"toc-text\">创建工程</span></a></li><li class=\"toc-item toc-level-1\"><a class=\"toc-link\" href=\"#%E4%B8%BA%E7%AA%97%E5%8F%A3%E6%B7%BB%E5%8A%A0%E7%AA%97%E4%BD%93%E9%83%A8%E4%BB%B6\"><span class=\"toc-text\">为窗口添加窗体部件</span></a></li><li class=\"toc-item toc-level-1\"><a class=\"toc-link\" href=\"#%E4%B8%BA%E7%AA%97%E5%8F%A3%E5%86%85%E9%83%A8%E6%B7%BB%E5%8A%A0%E9%80%BB%E8%BE%91\"><span class=\"toc-text\">为窗口内部添加逻辑</span></a></li><li class=\"toc-item toc-level-1\"><a class=\"toc-link\" href=\"#%E7%94%9F%E6%88%90exe%E6%96%87%E4%BB%B6\"><span class=\"toc-text\">生成exe文件</span></a></li></ol>","author":{"name":"祥瑞","slug":"blog-author","avatar":"https://s1.ax1x.com/2022/04/08/L9tIA0.jpg","link":"/","description":"励志成为野生钢铁侠-稚晖君的小弟 <br /> @ <b>B站：电工渣</b>","socials":{"github":"","twitter":"","stackoverflow":"","wechat":"","qq":"","weibo":"","zhihu":"","csdn":"","juejin":"","customs":{}}},"mapped":true,"prev_post":{"title":"16届智能车比赛","uid":"81d693b10474421070e94aab75f243ef","slug":"智能车比赛","date":"2021-10-29T05:25:21.000Z","updated":"2021-10-29T14:19:45.327Z","comments":true,"path":"api/articles/智能车比赛.json","keywords":null,"cover":[],"text":"引言现在是2021年10月29日，距离16届智能车比赛已经过去了2个多月了，马上17届智能车也要开始了，一直没有做总结是有原因的，因为当时真的真的真的很惨，甚至没有取得成绩（当时的规则是跑完一圈就可以拿优秀奖），对不起一直陪在我们身边的徐老师，更对自己没有努力而难过。其实很刚结束...","link":"","photos":[],"count_time":{"symbolsCount":"1.8k","symbolsTime":"2 mins."},"categories":[],"tags":[{"name":"智能车","slug":"智能车","count":2,"path":"api/tags/智能车.json"}],"author":{"name":"祥瑞","slug":"blog-author","avatar":"https://s1.ax1x.com/2022/04/08/L9tIA0.jpg","link":"/","description":"励志成为野生钢铁侠-稚晖君的小弟 <br /> @ <b>B站：电工渣</b>","socials":{"github":"","twitter":"","stackoverflow":"","wechat":"","qq":"","weibo":"","zhihu":"","csdn":"","juejin":"","customs":{}}}},"next_post":{"title":"MD常用语句","uid":"cdd0ed69b5efeea0c1519efc87c7f99f","slug":"MD常用语句","date":"2021-10-18T08:25:35.000Z","updated":"2021-12-23T13:27:39.241Z","comments":true,"path":"api/articles/MD常用语句.json","keywords":null,"cover":null,"text":"图片1,使用html方法引入 &lt;img src=\"https://alexcld.com/images/pengyuyan.jpg\" width=256 height=256 /> &lt;img src=\"https://alexcld.com/images/pengyu...","link":"","photos":[],"count_time":{"symbolsCount":"1.1k","symbolsTime":"1 mins."},"categories":[{"name":"hexo编辑","slug":"hexo编辑","count":1,"path":"api/categories/hexo编辑.json"}],"tags":[{"name":"记录","slug":"记录","count":3,"path":"api/tags/记录.json"}],"author":{"name":"祥瑞","slug":"blog-author","avatar":"https://s1.ax1x.com/2022/04/08/L9tIA0.jpg","link":"/","description":"励志成为野生钢铁侠-稚晖君的小弟 <br /> @ <b>B站：电工渣</b>","socials":{"github":"","twitter":"","stackoverflow":"","wechat":"","qq":"","weibo":"","zhihu":"","csdn":"","juejin":"","customs":{}}}}}