{"name":"课程学习","slug":"课程学习","count":6,"postlist":[{"title":"EDA课程学习","uid":"3aa30f86d5e7a5fe52d49f283f39878f","slug":"EDA课程学习","date":"2021-11-29T10:31:08.000Z","updated":"2022-01-03T14:29:31.298Z","comments":true,"path":"api/articles/EDA课程学习.json","keywords":null,"cover":[],"text":"EDA课程学习这个篇博客主要是我在完成我的EDA课程在学习通上面的章节练习时，做的笔记。 (这个脑图是老师提高的哈，非常耐撕！) 记忆宫殿 英文 中文 ISP 在系统编程 LUT（Look-Up-Table） 查找表 LAB 逻辑阵列块 FPGA 现场可编程逻辑门阵列 OTP 一...","link":"","photos":[],"count_time":{"symbolsCount":"1.8k","symbolsTime":"2 mins."},"categories":[{"name":"课程学习","slug":"课程学习","count":6,"path":"api/categories/课程学习.json"}],"tags":[{"name":"FPGA","slug":"FPGA","count":2,"path":"api/tags/FPGA.json"}],"author":{"name":"Aurora","slug":"blog-author","avatar":"https://img-blog.csdnimg.cn/20210313122054101.png","link":"/","description":"","socials":{"github":"","twitter":"","stackoverflow":"","wechat":"","qq":"","weibo":"","zhihu":"","csdn":"","juejin":"","customs":{}}}},{"title":"嵌入式系统设计与应用","uid":"0f8d9761b605a0589f071d0c0d4184a4","slug":"嵌入式系统设计与应用","date":"2022-03-01T02:43:21.000Z","updated":"2022-03-15T05:58:16.967Z","comments":true,"path":"api/articles/嵌入式系统设计与应用.json","keywords":null,"cover":[],"text":"前言材料及参考书获取资源 书号是实体书背面的二维码 相关网站www.arm.com www.21ic.com/embed/ www.home.eeworld.com.cn（电子工程世界） bbs.elecfans.com(电子发烧友) 感觉不是很活跃 第一章第一节课嵌入式概念：嵌...","link":"","photos":[],"count_time":{"symbolsCount":"3.1k","symbolsTime":"3 mins."},"categories":[{"name":"课程学习","slug":"课程学习","count":6,"path":"api/categories/课程学习.json"}],"tags":[{"name":"linux","slug":"linux","count":4,"path":"api/tags/linux.json"}],"author":{"name":"Aurora","slug":"blog-author","avatar":"https://img-blog.csdnimg.cn/20210313122054101.png","link":"/","description":"","socials":{"github":"","twitter":"","stackoverflow":"","wechat":"","qq":"","weibo":"","zhihu":"","csdn":"","juejin":"","customs":{}}}},{"title":"微机原理与接口技术复习笔记","uid":"c7c7d3f34d67a88be91b6acae917b627","slug":"微机原理与接口技术复习笔记","date":"2021-12-19T08:15:17.000Z","updated":"2022-01-03T09:19:29.533Z","comments":true,"path":"api/articles/微机原理与接口技术复习笔记.json","keywords":null,"cover":[],"text":"OK，这是在大三上学期的期末时，写的复习笔记，现在距离考试还有10天左右的时间，我得在这十天内把这学期学习的课程知识全部过一遍，并练一些编程题目。 先把沈老师分享的脑图，记录一下 脑图大纲 这图上面除了右边的具体知识，还有左上角的tips，怎么学？ 这是一个很重要的问题，有些时候...","link":"","photos":[],"count_time":{"symbolsCount":"5.1k","symbolsTime":"5 mins."},"categories":[{"name":"课程学习","slug":"课程学习","count":6,"path":"api/categories/课程学习.json"}],"tags":[{"name":"汇编","slug":"汇编","count":2,"path":"api/tags/汇编.json"}],"author":{"name":"Aurora","slug":"blog-author","avatar":"https://img-blog.csdnimg.cn/20210313122054101.png","link":"/","description":"","socials":{"github":"","twitter":"","stackoverflow":"","wechat":"","qq":"","weibo":"","zhihu":"","csdn":"","juejin":"","customs":{}}}},{"title":"数码管动态显示（VHDL）","uid":"e025b4b43a23185465e9613af8a1c518","slug":"数码管动态显示(VHDL)","date":"2021-12-01T13:35:17.000Z","updated":"2021-12-19T08:23:02.761Z","comments":true,"path":"api/articles/数码管动态显示(VHDL).json","keywords":null,"cover":[],"text":"VHDL动态显示4位数码管电路我这里的实验室通过拨码开关计数，然后通过数码管来显示，并没有对按键进行消抖处理。 一、动态数码管是什么？实际上很多两个以上的数码管都是动态数码管，设计成这样的真正目的是为了节约硬件资源，使用少量的引脚就可以点亮多个数码管。 多位数码管的数据端口实际上...","link":"","photos":[],"count_time":{"symbolsCount":"2.1k","symbolsTime":"2 mins."},"categories":[{"name":"课程学习","slug":"课程学习","count":6,"path":"api/categories/课程学习.json"}],"tags":[{"name":"FPGA","slug":"FPGA","count":2,"path":"api/tags/FPGA.json"}],"author":{"name":"Aurora","slug":"blog-author","avatar":"https://img-blog.csdnimg.cn/20210313122054101.png","link":"/","description":"","socials":{"github":"","twitter":"","stackoverflow":"","wechat":"","qq":"","weibo":"","zhihu":"","csdn":"","juejin":"","customs":{}}}},{"title":"汇编刷题","uid":"0e9eaaf753227dae6c8b950fc994c974","slug":"汇编刷题","date":"2021-12-28T13:09:27.000Z","updated":"2022-03-13T15:30:58.448Z","comments":true,"path":"api/articles/汇编刷题.json","keywords":null,"cover":null,"text":" (简答题)从键盘输入两个 0-9 之间的数据求和并显示 CODES SEGMENT ASSUME CS:CODES START: MOV AH,01H INT 21H 输入数字1 MOV BL,AL MOV AH,01H 输入数字2 INT 21H ADD AL,BL 加上数值...","link":"","photos":[],"count_time":{"symbolsCount":"3.9k","symbolsTime":"4 mins."},"categories":[{"name":"课程学习","slug":"课程学习","count":6,"path":"api/categories/课程学习.json"}],"tags":[{"name":"汇编","slug":"汇编","count":2,"path":"api/tags/汇编.json"}],"author":{"name":"Aurora","slug":"blog-author","avatar":"https://img-blog.csdnimg.cn/20210313122054101.png","link":"/","description":"","socials":{"github":"","twitter":"","stackoverflow":"","wechat":"","qq":"","weibo":"","zhihu":"","csdn":"","juejin":"","customs":{}}}},{"title":"通信原理","uid":"a62551fd56e2837b6f4afeba433d6170","slug":"通信原理","date":"2021-12-20T12:19:42.000Z","updated":"2021-12-20T13:20:08.805Z","comments":true,"path":"api/articles/通信原理.json","keywords":null,"cover":[],"text":"&lt;&lt;现代通信原理&gt;&gt;，是我在大三上学期学习的课程，因为想混git的小绿点，以及记录一下，所以把复习（学习）笔记，上传到blog上面来了。 🙂🙂🙂🙂🙂🙂 现代通信原理 根据学习通上老师设置的章节，可分为 绪论、通信系统中的信号信道和噪声、模拟调制系统、差错控...","link":"","photos":[],"count_time":{"symbolsCount":618,"symbolsTime":"1 mins."},"categories":[{"name":"课程学习","slug":"课程学习","count":6,"path":"api/categories/课程学习.json"}],"tags":[{"name":"信号","slug":"信号","count":1,"path":"api/tags/信号.json"}],"author":{"name":"Aurora","slug":"blog-author","avatar":"https://img-blog.csdnimg.cn/20210313122054101.png","link":"/","description":"","socials":{"github":"","twitter":"","stackoverflow":"","wechat":"","qq":"","weibo":"","zhihu":"","csdn":"","juejin":"","customs":{}}}}]}